dester.py
dester-0.3.dist-info/entry_points.txt
dester-0.3.dist-info/LICENSE
dester-0.3.dist-info/WHEEL
dester-0.3.dist-info/METADATA
dester-0.3.dist-info/RECORD
