Metadata-Version: 2.1
Name: dester
Version: 0.3
Summary: A linter to modify LaTeX files.
Author-email: Krystyna Kalinchuk <christinakalinchuk@gmail.com>
Requires-Python: >3.7
Classifier: License :: OSI Approved :: MIT License
Requires-Dist: click==8.1.3
Project-URL: Home, https://github.com/kalinchukkristina/dester-linter
